term_image/__init__.py
term_image/ctlseqs.py
term_image/exceptions.py
term_image/utils.py
term_image/image/__init__.py
term_image/image/block.py
term_image/image/common.py
term_image/image/iterm2.py
term_image/image/kitty.py
term_image/widget/__init__.py
term_image/widget/urwid.py
term_image_qpython-0.7.2.1.dist-info/METADATA
term_image_qpython-0.7.2.1.dist-info/WHEEL
term_image_qpython-0.7.2.1.dist-info/top_level.txt
term_image_qpython-0.7.2.1.dist-info/RECORD
